sidif/__init__.py
sidif/profiler.py
sidif/sidif.py
py_sidif-0.2.0.dist-info/METADATA
py_sidif-0.2.0.dist-info/WHEEL
py_sidif-0.2.0.dist-info/licenses/LICENSE
py_sidif-0.2.0.dist-info/RECORD
