Metadata-Version: 2.3
Name: py-sidif
Version: 0.2.0
Dynamic: Summary
Project-URL: Home, https://github.com/WolfgangFahl/py-sidif
Project-URL: Documentation, https://wiki.bitplan.com/index.php/Py-sidif
Project-URL: Source, https://github.com/WolfgangFahl/py-sidif
Author-email: Wolfgang Fahl <wf@bitplan.com>
Maintainer-email: Wolfgang Fahl <wf@bitplan.com>
License-Expression: Apache-2.0
License-File: LICENSE
Classifier: Development Status :: 4 - Beta
Classifier: Environment :: Web Environment
Classifier: Intended Audience :: Developers
Classifier: Intended Audience :: Education
Classifier: Intended Audience :: Science/Research
Classifier: License :: OSI Approved :: Apache Software License
Classifier: Operating System :: OS Independent
Classifier: Programming Language :: Python :: 3 :: Only
Classifier: Programming Language :: Python :: 3.9
Classifier: Programming Language :: Python :: 3.10
Classifier: Programming Language :: Python :: 3.11
Classifier: Programming Language :: Python :: 3.12
Classifier: Topic :: Software Development :: Libraries :: Python Modules
Requires-Python: >=3.9
Requires-Dist: pyparsing
Requires-Dist: xmltodict
Provides-Extra: test
Requires-Dist: green; extra == 'test'
